docs/Makefile
docs/api_reference.rst
docs/cheatsheet.rst
docs/conf.py
docs/developer_guide.rst
docs/extension_orfs.rst
docs/extension_seqs.rst
docs/extension_stats.rst
docs/how_to_columns.rst
docs/how_to_create.rst
docs/how_to_genomic_ops.rst
docs/how_to_inspect.rst
docs/how_to_map.rst
docs/how_to_overlap.rst
docs/how_to_pages.rst
docs/how_to_rows.rst
docs/how_to_sequences.rst
docs/how_to_write.rst
docs/index.rst
docs/installation.rst
docs/make.bat
docs/migration_cheatsheet.tsv
docs/migration_guide.rst
docs/pyranger_cli.rst
docs/pyranges_extensions.rst
docs/pyranges_module.rst
docs/pyranges_objects.rst
docs/range_frame.rst
docs/requirements.txt
docs/tutorial.rst
docs/_static/custom.css
docs/_templates/custom_method_summary.rst
pyranges1/__init__.py
pyranges1/cli.py
pyranges1/docs
pyranges1/orfs.py
pyranges1/readers.py
pyranges1/seqs.py
pyranges1/stats.py
pyranges1/core/__init__.py
pyranges1/core/assistant.py
pyranges1/core/empty.py
pyranges1/core/example_data.py
pyranges1/core/loci_getter.py
pyranges1/core/multioverlap.py
pyranges1/core/names.py
pyranges1/core/options.py
pyranges1/core/out.py
pyranges1/core/pyranges_groupby.py
pyranges1/core/pyranges_helpers.py
pyranges1/core/pyranges_main.py
pyranges1/core/random.py
pyranges1/core/tostring.py
pyranges1/core/version.py
pyranges1/data/__init__.py
pyranges1/data/aorta.bed
pyranges1/data/aorta2.bed
pyranges1/data/bigwig.bw
pyranges1/data/chipseq.bed
pyranges1/data/chipseq_background.bed
pyranges1/data/chromsizes.bed
pyranges1/data/cpg.bed
pyranges1/data/ensembl.gtf
pyranges1/data/ensembl_human.gtf.gz
pyranges1/data/exons.bed
pyranges1/data/f1.bed
pyranges1/data/f2.bed
pyranges1/data/gencode_human.gtf.gz
pyranges1/data/lamina.bed
pyranges1/data/ncbi.fasta
pyranges1/data/ncbi.fasta.fai
pyranges1/data/ncbi.gff.gz
pyranges1/data/smaller.bam
pyranges1/data/ucsc_human.bed.gz
pyranges1/ext/__init__.py
pyranges1/ext/orfs.py
pyranges1/ext/seqs.py
pyranges1/ext/stats.py
pyranges1/methods/__init__.py
pyranges1-1.2.0.dist-info/licenses/LICENSE
pyranges1-1.2.0.dist-info/METADATA
pyranges1-1.2.0.dist-info/WHEEL
pyranges1-1.2.0.dist-info/entry_points.txt
pyranges1-1.2.0.dist-info/top_level.txt
pyranges1-1.2.0.dist-info/RECORD
