Metadata-Version: 2.4
Name: pyranges1
Version: 1.2.0
Summary: GenomicRanges for Python.
Author-email: Endre Bakken Stovner <endbak@hey.com>, Marco Mariotti <marco.mariotti@ub.edu>
License: MIT
Project-URL: Homepage, http://github.com/pyranges/pyranges_1.x
Keywords: bioinformatics,genomicranges,genomics
Classifier: Programming Language :: Python :: 3
Classifier: Development Status :: 4 - Beta
Classifier: Environment :: Other Environment
Classifier: Intended Audience :: Developers
Classifier: Intended Audience :: Science/Research
Classifier: License :: OSI Approved :: MIT License
Classifier: Operating System :: POSIX :: Linux
Classifier: Operating System :: MacOS :: MacOS X
Classifier: Topic :: Scientific/Engineering
Requires-Python: >=3.12.0
License-File: LICENSE
Requires-Dist: pandas<3.0.0
Requires-Dist: tabulate
Requires-Dist: natsort
Requires-Dist: ruranges>=0.0.14
Provides-Extra: add-ons
Requires-Dist: pyrle>=0.0.43; extra == "add-ons"
Requires-Dist: bamread; extra == "add-ons"
Requires-Dist: pyfaidx; extra == "add-ons"
Requires-Dist: pyBigWig; extra == "add-ons"
Requires-Dist: joblib; extra == "add-ons"
Provides-Extra: dev
Requires-Dist: tox; extra == "dev"
Requires-Dist: ruff==0.14.1; extra == "dev"
Requires-Dist: pyright; extra == "dev"
Requires-Dist: pandas-stubs; extra == "dev"
Requires-Dist: types-tabulate; extra == "dev"
Requires-Dist: pytest-watcher; extra == "dev"
Requires-Dist: pytest-xdist; extra == "dev"
Provides-Extra: docs
Requires-Dist: sphinx; extra == "docs"
Requires-Dist: sphinx_rtd_theme; extra == "docs"
Requires-Dist: sphinx-autoapi; extra == "docs"
Requires-Dist: sphinxcontrib-napoleon; extra == "docs"
Provides-Extra: cli
Requires-Dist: fire; extra == "cli"
Provides-Extra: all
Requires-Dist: pyranges1[add-ons]; extra == "all"
Requires-Dist: pyranges1[dev]; extra == "all"
Requires-Dist: pyranges1[docs]; extra == "all"
Requires-Dist: pyranges1[cli]; extra == "all"
Dynamic: license-file
